{"hash":"4c9b580826c208e2cc257f60390b894c71c0ddcf","data":{"technology":{"title":"Fastify","belongsTo":{"totalCount":1,"pageInfo":{"totalPages":1,"currentPage":1},"edges":[{"node":{"title":"My Personal Site v2","image":"/covers/projects/dorich-site-v2.jpeg","path":"/portfolio/projects/dorich-site-v2/","summary":"I needed a resource that would demonstrate my web development competence in \nitself and simply by describing what I can.\n\nHere information is provided directly about me, here projects \nthat I want to share with others are collected, here resumes have...","tags":[{"title":"frontend"},{"title":"backend"},{"title":"SEO"},{"title":"prod"}]}}]}},"technologies":{"edges":[{"node":{"title":"Bootstrap","path":"/portfolio/technologies/Bootstrap/"}},{"node":{"title":"Chart.js","path":"/portfolio/technologies/Chart.js/"}},{"node":{"title":"Dropbox","path":"/portfolio/technologies/Dropbox/"}},{"node":{"title":"Express","path":"/portfolio/technologies/Express/"}},{"node":{"title":"Fastify","path":"/portfolio/technologies/Fastify/"}},{"node":{"title":"Firebase","path":"/portfolio/technologies/Firebase/"}},{"node":{"title":"JQuery","path":"/portfolio/technologies/JQuery/"}},{"node":{"title":"MongoDB","path":"/portfolio/technologies/MongoDB/"}},{"node":{"title":"Mongoose","path":"/portfolio/technologies/Mongoose/"}},{"node":{"title":"Node.js","path":"/portfolio/technologies/Node.js/"}},{"node":{"title":"Nuxt.js","path":"/portfolio/technologies/Nuxt.js/"}},{"node":{"title":"PostgreSQL","path":"/portfolio/technologies/PostgreSQL/"}},{"node":{"title":"Sequelize ORM","path":"/portfolio/technologies/Sequelize%20ORM/"}},{"node":{"title":"Vue.js","path":"/portfolio/technologies/Vue.js/"}},{"node":{"title":"Vuetify","path":"/portfolio/technologies/Vuetify/"}}]}},"context":{}}