{"hash":"cae65cf17d4f680647d1daf7e622753cc61430ab","data":{"repos":{"totalCount":12,"pageInfo":{"totalPages":2,"currentPage":1},"edges":[{"node":{"id":"454080323","name":"th2-docs","full_name":"th2-net/th2-docs","owner":{"login":"th2-net","type":"Organization","html_url":"https://github.com/th2-net","avatar_url":"https://avatars.githubusercontent.com/u/73948563?v=4"},"description":"","html_url":"https://github.com/th2-net/th2-docs","stargazers_count":3,"language":{"name":"Vue","color":"#41b883","icon":"https://cdn.jsdelivr.net/gh/devicons/devicon/icons/vuejs/vuejs-original.svg"},"releases":[{"name":"v1.0 Static Site Generated (Beta)","tag_name":"v1.0-beta","html_url":"https://github.com/th2-net/th2-docs/releases/tag/v1.0-beta"},{"name":"th2 docs (Nuxt) v0.0.1","tag_name":"v0.0.1","html_url":"https://github.com/th2-net/th2-docs/releases/tag/v0.0.1"}]}},{"node":{"id":"521584510","name":"th2-docs-schema","full_name":"d0rich/th2-docs-schema","owner":{"login":"d0rich","type":"User","html_url":"https://github.com/d0rich","avatar_url":"https://avatars.githubusercontent.com/u/51794590?v=4"},"description":"","html_url":"https://github.com/d0rich/th2-docs-schema","stargazers_count":0,"language":null,"releases":[]}},{"node":{"id":"257043690","name":"d0rich.github.io","full_name":"d0rich/d0rich.github.io","owner":{"login":"d0rich","type":"User","html_url":"https://github.com/d0rich","avatar_url":"https://avatars.githubusercontent.com/u/51794590?v=4"},"description":"🌐 Just website about myself","html_url":"https://github.com/d0rich/d0rich.github.io","stargazers_count":1,"language":{"name":"Vue","color":"#41b883","icon":"https://cdn.jsdelivr.net/gh/devicons/devicon/icons/vuejs/vuejs-original.svg"},"releases":[]}},{"node":{"id":"525043168","name":"th2-dependencies","full_name":"d0rich/th2-dependencies","owner":{"login":"d0rich","type":"User","html_url":"https://github.com/d0rich","avatar_url":"https://avatars.githubusercontent.com/u/51794590?v=4"},"description":"🖇️ Script for analysis of th2-net organization and creating dependencies graph. ","html_url":"https://github.com/d0rich/th2-dependencies","stargazers_count":0,"language":{"name":"TypeScript","color":"#3178c6","icon":"https://cdn.jsdelivr.net/gh/devicons/devicon/icons/typescript/typescript-original.svg"},"releases":[]}},{"node":{"id":"530371108","name":"th2-cli","full_name":"d0rich/th2-cli","owner":{"login":"d0rich","type":"User","html_url":"https://github.com/d0rich","avatar_url":"https://avatars.githubusercontent.com/u/51794590?v=4"},"description":"👨‍💻 CLI for managing th2 infrastructure in Kubernetes cluster","html_url":"https://github.com/d0rich/th2-cli","stargazers_count":1,"language":{"name":"Python","color":"#3572A5","icon":"https://cdn.jsdelivr.net/gh/devicons/devicon/icons/python/python-original.svg"},"releases":[{"name":"v1.7.3","tag_name":"v1.7.3","html_url":"https://github.com/d0rich/th2-cli/releases/tag/v1.7.3"},{"name":"v1.7.2","tag_name":"v1.7.2","html_url":"https://github.com/d0rich/th2-cli/releases/tag/v1.7.2"},{"name":"v1.7.1","tag_name":"v1.7.1","html_url":"https://github.com/d0rich/th2-cli/releases/tag/v1.7.1"},{"name":"v1.7.0","tag_name":"v1.7.0","html_url":"https://github.com/d0rich/th2-cli/releases/tag/v1.7.0"},{"name":"v1.5.0","tag_name":"v1.5.0","html_url":"https://github.com/d0rich/th2-cli/releases/tag/v1.5.0"},{"name":"v0.2.2 Prerequisites message","tag_name":"v0.2.2","html_url":"https://github.com/d0rich/th2-cli/releases/tag/v0.2.2"},{"name":"v0.2.1 Change temp charts location","tag_name":"v0.2.1","html_url":"https://github.com/d0rich/th2-cli/releases/tag/v0.2.1"},{"name":"v0.2.0","tag_name":"v0.2.0","html_url":"https://github.com/d0rich/th2-cli/releases/tag/v0.2.0"},{"name":"v0.1.0 Test release","tag_name":"v0.1.0","html_url":"https://github.com/d0rich/th2-cli/releases/tag/v0.1.0"}]}},{"node":{"id":"391897074","name":"d0rich","full_name":"d0rich/d0rich","owner":{"login":"d0rich","type":"User","html_url":"https://github.com/d0rich","avatar_url":"https://avatars.githubusercontent.com/u/51794590?v=4"},"description":"","html_url":"https://github.com/d0rich/d0rich","stargazers_count":0,"language":null,"releases":[]}}]}},"context":{}}